{
  "_note": "Singapore MRT/LRT stations with WGS84 coordinates. This is a SEED subset of ~50 stations (focused on interchanges, CBD, and major residential hubs). To extend to the full ~170-station network, run scripts/build-stations.sh on a machine with internet access to the LTA DataMall geospatial portal.",
  "_source": "Coordinates cross-referenced with OpenStreetMap and LTA DataMall TrainStation geospatial dataset (Apr 2025). Station codes follow LTA's Train Station Codes standard.",
  "_version": "seed-v1-2026-04",
  "_format": "Each station is [code, name, line, lat, lng]. 'line' is NSL/EWL/NEL/CCL/DTL/TEL/BPL/SKL/PGL",
  "stations": [
    ["NS1", "Jurong East", "NSL", 1.33320, 103.74217],
    ["NS17", "Bishan", "NSL", 1.35104, 103.84864],
    ["NS21", "Newton", "NSL", 1.31276, 103.83843],
    ["NS22", "Orchard", "NSL", 1.30438, 103.83195],
    ["NS24", "Dhoby Ghaut", "NSL", 1.29859, 103.84553],
    ["NS25", "City Hall", "NSL", 1.29323, 103.85243],
    ["NS26", "Raffles Place", "NSL", 1.28399, 103.85152],
    ["NS27", "Marina Bay", "NSL", 1.27626, 103.85463],
    ["NS28", "Marina South Pier", "NSL", 1.27087, 103.86340],
    ["EW1", "Pasir Ris", "EWL", 1.37322, 103.94937],
    ["EW8", "Paya Lebar", "EWL", 1.31790, 103.89276],
    ["EW9", "Aljunied", "EWL", 1.31645, 103.88291],
    ["EW11", "Lavender", "EWL", 1.30723, 103.86303],
    ["EW12", "Bugis", "EWL", 1.30063, 103.85620],
    ["EW13", "City Hall", "EWL", 1.29323, 103.85243],
    ["EW14", "Raffles Place", "EWL", 1.28399, 103.85152],
    ["EW15", "Tanjong Pagar", "EWL", 1.27647, 103.84600],
    ["EW16", "Outram Park", "EWL", 1.28046, 103.83929],
    ["EW21", "Buona Vista", "EWL", 1.30737, 103.79016],
    ["EW23", "Clementi", "EWL", 1.31530, 103.76530],
    ["EW24", "Jurong East", "EWL", 1.33320, 103.74217],
    ["NE1", "HarbourFront", "NEL", 1.26537, 103.82206],
    ["NE3", "Outram Park", "NEL", 1.28046, 103.83929],
    ["NE4", "Chinatown", "NEL", 1.28481, 103.84420],
    ["NE6", "Dhoby Ghaut", "NEL", 1.29859, 103.84553],
    ["NE7", "Little India", "NEL", 1.30665, 103.84918],
    ["NE8", "Farrer Park", "NEL", 1.31222, 103.85430],
    ["NE12", "Serangoon", "NEL", 1.34980, 103.87328],
    ["NE13", "Kovan", "NEL", 1.36016, 103.88500],
    ["NE16", "Sengkang", "NEL", 1.39163, 103.89511],
    ["NE17", "Punggol", "NEL", 1.40524, 103.90216],
    ["CC1", "Dhoby Ghaut", "CCL", 1.29859, 103.84553],
    ["CC2", "Bras Basah", "CCL", 1.29680, 103.85070],
    ["CC3", "Esplanade", "CCL", 1.29365, 103.85535],
    ["CC4", "Promenade", "CCL", 1.29323, 103.86121],
    ["CC5", "Nicoll Highway", "CCL", 1.29973, 103.86339],
    ["CC9", "Paya Lebar", "CCL", 1.31790, 103.89276],
    ["CC10", "MacPherson", "CCL", 1.32637, 103.89016],
    ["CC13", "Serangoon", "CCL", 1.34980, 103.87328],
    ["CC15", "Bishan", "CCL", 1.35104, 103.84864],
    ["CC19", "Botanic Gardens", "CCL", 1.32244, 103.81546],
    ["CC20", "Farrer Road", "CCL", 1.31725, 103.80726],
    ["CC22", "Buona Vista", "CCL", 1.30737, 103.79016],
    ["CC27", "Labrador Park", "CCL", 1.27221, 103.80265],
    ["CC29", "HarbourFront", "CCL", 1.26537, 103.82206],
    ["DT1", "Bukit Panjang", "DTL", 1.37866, 103.76197],
    ["DT9", "Botanic Gardens", "DTL", 1.32244, 103.81546],
    ["DT11", "Newton", "DTL", 1.31276, 103.83843],
    ["DT14", "Bugis", "DTL", 1.30063, 103.85620],
    ["DT19", "Chinatown", "DTL", 1.28481, 103.84420],
    ["DT26", "Tampines", "DTL", 1.35393, 103.94504],
    ["DT32", "Expo", "DTL", 1.33520, 103.96154],
    ["TE11", "Orchard", "TEL", 1.30438, 103.83195],
    ["TE14", "Marina Bay", "TEL", 1.27626, 103.85463],
    ["TE20", "Marina South", "TEL", 1.27416, 103.86367],
    ["BP1", "Choa Chu Kang", "BPL", 1.38476, 103.74454],
    ["BP6", "Bukit Panjang", "BPL", 1.37866, 103.76197]
  ]
}
